mimiallstartools/__init__.py
mimiallstartools/mimi.py
mimiallstartools-0.1.dist-info/METADATA
mimiallstartools-0.1.dist-info/WHEEL
mimiallstartools-0.1.dist-info/top_level.txt
mimiallstartools-0.1.dist-info/RECORD
